README.md
pytest_sequence_markers.py
setup.py
pytest_sequence_markers.egg-info/PKG-INFO
pytest_sequence_markers.egg-info/SOURCES.txt
pytest_sequence_markers.egg-info/dependency_links.txt
pytest_sequence_markers.egg-info/entry_points.txt
pytest_sequence_markers.egg-info/top_level.txt