Metadata-Version: 2.1
Name: pytest-sequence-markers
Version: 0.0.2
Summary: Pytest plugin for sequencing markers for execution of tests
Home-page: https://github.com/siddheshsathe/pytest-plugins
Author: Siddhesh Sathe
Author-email: siddheshsathe@rediffmail.com
License: GNU
Project-URL: Source, https://github.com/siddheshsathe/pytest-plugins
Platform: UNKNOWN
Classifier: Development Status :: 5 - Production/Stable
Classifier: Programming Language :: Python :: 3
Classifier: Intended Audience :: Developers
Classifier: Operating System :: OS Independent
Requires: pytest
